[
  {
    "method": "GET",
    "path": "/v1/ping",
    "name": "github.com/ClanceyLu/echo-api/routers.Init.func1"
  },
  {
    "method": "GET",
    "path": "/ping",
    "name": "github.com/ClanceyLu/echo-api/routers.Init.func2"
  },
  {
    "method": "POST",
    "path": "/register",
    "name": "github.com/ClanceyLu/echo-api/routers/v1.Register"
  },
  {
    "method": "PUT",
    "path": "/user/:id",
    "name": "github.com/ClanceyLu/echo-api/routers/v1.UpdateUser"
  },
  {
    "method": "GET",
    "path": "/user/:id",
    "name": "github.com/ClanceyLu/echo-api/routers/v1.GetUser"
  }
]